dist/ka_air_dfs-2023.2.1.tar.gz
ka_air_dfs/__init__.py
ka_air_dfs/__version__.py
ka_air_dfs/bin/daf_tsk_mon.2
ka_air_dfs/bin/dfs_rbk.1
ka_air_dfs/bin/dfs_rbk.2
ka_air_dfs/bin/dfs_rbk.sh
ka_air_dfs/bin/dfs_rbk_str.1
ka_air_dfs/bin/dfs_rbk_str.2
ka_air_dfs/bin/dfs_rbk_str.sh
ka_air_dfs/bin/dfs_tsk.1
ka_air_dfs/bin/dfs_tsk.2
ka_air_dfs/bin/dfs_tsk.sh
ka_air_dfs/bin/dfs_tsk_all.1
ka_air_dfs/bin/dfs_tsk_all.2
ka_air_dfs/bin/dfs_tsk_all.sh
ka_air_dfs/bin/dfs_tsk_mon.1
ka_air_dfs/bin/dfs_tsk_mon.2
ka_air_dfs/bin/dfs_tsk_mon.sh
ka_air_dfs/bin/dfs_tsk_str.1
ka_air_dfs/bin/dfs_tsk_str.2
ka_air_dfs/bin/dfs_tsk_str.sh
ka_air_dfs/data/__init__.py
ka_air_dfs/data/dfs.yaml
ka_air_dfs/dfs/__init__.py
ka_air_dfs/dfs/__main__.py
ka_air_dfs/dfs/do.py
ka_air_dfs/dfs/parms.py
ka_air_dfs/docs/ERRORS.txt
ka_air_dfs/docs/Makefile
ka_air_dfs/docs/conf.py
ka_air_dfs/docs/index.rst
ka_air_dfs/docs/make.bat
ka_air_dfs/docs/_build/doctrees/environment.pickle
ka_air_dfs/docs/_build/doctrees/index.doctree
ka_air_dfs/docs/_build/html/genindex.html
ka_air_dfs/docs/_build/html/index.html
ka_air_dfs/docs/_build/html/objects.inv
ka_air_dfs/docs/_build/html/search.html
ka_air_dfs/docs/_build/html/searchindex.js
ka_air_dfs/docs/_build/html/_sources/index.rst.txt
ka_air_dfs/docs/_build/html/_static/alabaster.css
ka_air_dfs/docs/_build/html/_static/basic.css
ka_air_dfs/docs/_build/html/_static/custom.css
ka_air_dfs/docs/_build/html/_static/doctools.js
ka_air_dfs/docs/_build/html/_static/documentation_options.js
ka_air_dfs/docs/_build/html/_static/file.png
ka_air_dfs/docs/_build/html/_static/language_data.js
ka_air_dfs/docs/_build/html/_static/minus.png
ka_air_dfs/docs/_build/html/_static/plus.png
ka_air_dfs/docs/_build/html/_static/pygments.css
ka_air_dfs/docs/_build/html/_static/searchtools.js
ka_air_dfs/docs/_build/html/_static/sphinx_highlight.js
ka_air_dfs/docs/_build/man/controlmapplications.1
ka_air_dfs/uts/__init__.py
ka_air_dfs/uts/fac.py
ka_air_dfs/uts/src.py
ka_air_dfs/uts/uts.py
ka_air_dfs-2023.2.1.dist-info/LICENSE.txt
ka_air_dfs-2023.2.1.dist-info/METADATA
ka_air_dfs-2023.2.1.dist-info/WHEEL
ka_air_dfs-2023.2.1.dist-info/entry_points.txt
ka_air_dfs-2023.2.1.dist-info/top_level.txt
ka_air_dfs-2023.2.1.dist-info/RECORD
